herja/__init__.py
herja/__main__.py
herja/assertions.py
herja/common.py
herja/constants.py
herja/conversions.py
herja/decorators.py
herja/fs.py
herja/logging/__init__.py
herja/logging/decorators.py
herja/net.py
herja/settings/__init__.py
herja/settings/__main__.py
herja-0.1.0.dist-info/LICENSE
herja-0.1.0.dist-info/WHEEL
herja-0.1.0.dist-info/METADATA
herja-0.1.0.dist-info/RECORD
