Metadata-Version: 2.1
Name: herja
Version: 0.1.0
Summary: A python repository for quality of life purposes.
Author: IanWernecke
Author-email: IanWernecke@protonmail.com
Requires-Python: >=3.7,<4.0
Classifier: Programming Language :: Python :: 3
Classifier: Programming Language :: Python :: 3.7
Classifier: Programming Language :: Python :: 3.8
Requires-Dist: beautifulsoup4 (>=4.8.2,<5.0.0)
Requires-Dist: requests (>=2.23.0,<3.0.0)
